aiocoingecko/__init__.py
aiocoingecko/api.py
aiocoingecko/errors.py
aiocoingecko-1.0.0.dist-info/LICENSE
aiocoingecko-1.0.0.dist-info/METADATA
aiocoingecko-1.0.0.dist-info/WHEEL
aiocoingecko-1.0.0.dist-info/top_level.txt
aiocoingecko-1.0.0.dist-info/RECORD
