Metadata-Version: 2.1
Name: aiocoingecko
Version: 1.0.0
Summary: Asynchronous Python wrapper for the CoinGecko API
Home-page: https://github.com/regulad/aiocoingecko
Author: regulad
Author-email: regulad@outlook.com
License: MIT
Download-URL: https://codeload.github.com/regulad/aiocoingecko/zip/refs/heads/main
Keywords: async,api
Platform: UNKNOWN
Classifier: Intended Audience :: Developers
Classifier: License :: OSI Approved :: MIT License
Classifier: Programming Language :: Python :: 3
Classifier: Programming Language :: Python :: 3.6
Classifier: Programming Language :: Python :: 3.7
Classifier: Programming Language :: Python :: 3.8
Classifier: Programming Language :: Python :: 3.9
License-File: LICENSE
Requires-Dist: aiohttp
Requires-Dist: typing-extensions
